safepackage/Confused.py
safepackage/__init__.py
safepackage/calc.py
safepackage-1337.0.3.dist-info/METADATA
safepackage-1337.0.3.dist-info/WHEEL
safepackage-1337.0.3.dist-info/top_level.txt
safepackage-1337.0.3.dist-info/RECORD
